{"9ME3095owzmq7edRXUfP8g==":"mbr-1-982x737.jpg","xbDKqBrnfq2CfHFpf5qTmQ==":"kisspng-smoking-ban-oklahoma-no-symbol-computer-icons-no-smoking-icon-5b248013812906.4280624315291187395291-124x124.png","e8ZUSEM5NTIfzNX65AIUlQ==":"mbr-1920x1280.jpg","Th1TFVT7ce45ub+yNi6USg==":"kisspng-smoking-ban-oklahoma-no-symbol-computer-icons-no-smoking-icon-5b248013812906.4280624315291187395291-192x192.png","ihlkf69UyfSmhSyJ1Jvc6w==":"jumbotron.jpg","+iJAlBcJ2hCxhbNdDL6BTQ==":"mbr-800x530.jpg","0OOE1Usrtktm437Z/qTMRQ==":"background2.jpg","GDrhFCA7dTyysoe9Vqy+Cw==":"giphy.gif","4+DzqXFpj/z2AIwVP9lcYQ==":"background5.jpg","NBeRvGcH5uJp6ycGjhXatA==":"background4.jpg","48fAzz3IiR0pTNLBUI/rUw==":"giphy%20(6).gif","Sd5huQ42Vzvpk7gZfAUbvg==":"giphy%20(7).gif","PKbIuWNsadOavWtbA7VYNA==":"giphy%20(1).gif","97dVmBG8rV/0whRKZdl0cA==":"mbr-1920x1271.jpg","I6M5CEYDDbQmtduYVCy5RQ==":"mbr-1200x918.jpg","LiUIORYxGXGMpCM1i0NnEA==":"06.jpg","Wl+xy3tOtuUOTLFCa0c4eA==":"mbr-1-1200x800.jpg","2v2S92Exw0hlX9G0GgQcwQ==":"mbr-2-1200x800.jpg","LOH6PtqnW3KOUM882FtTEA==":"mbr-3-1200x800.jpg","Ly+mdm63lVz6CqSX2vcU6g==":"background3.jpg","1W1hIINnJS6rMRaB0l+SDQ==":"mbr-7-1200x800.jpg","Q8kyWdiPLYJ/4F1Ss+9IyA==":"03.jpg","/IUEDjwmU9ZwDbiU41lfig==":"16807600_1546341852057738_5936864678199444006_n-2-510x509.jpg","dJhvwSMB5Q2gbhsXGiPn9Q==":"36430379_1741830119228477_3369267583034327040_n-510x680.jpg","JCwwxowIvpNFsiGu261Mzg==":"22492009_1955655184657554_5005538505865875105_n-510x513.jpg","uVflleKk87lfQnOAMP1rZw==":"crop%20(1)-444x794.jpg","CuBR4/L5cD2bHXzMaQjscg==":"dsc-27-1200x798.jpg","AztiR90HXEQ5GFl/28NIeg==":"dsc-31-510x339.jpg","YXWVcQ04qugCQ8dd+OVlUg==":"dsc-30-510x339.jpg","ttrVxBxrRORSF4kuTZZulA==":"dsc-29-510x339.jpg","k4+WgmhrGbYsN8J/MJPd4w==":"mbr-1920x1316.jpg","f2bqzRtRFc2Z3YJWzrf+LQ==":"29356954_1590025314384593_7246772579997858184_n-300x300.jpg","j++9Ghk4MnDq+QLFtHBJdw==":"42397420_341030566441280_5170702099633143808_n-280x280.jpg","NpsD4Ttv3zX3DILZjR/u8g==":"ichiro-300x400.jpg","c6Aoi4KRlnxiKg+Yzmgsfg==":"rio-300x532.jpg","CKabzAyO2lJSAmbQJnXQ4g==":"giphy%20(8).gif","Lm5Uia6yHE3/9QxP0NlDpA==":"giphy%20(3).gif","hYgHQSvjbUJnxr5DVdOIRA==":"cigerette%20wallpapers%20for%20desktop-759x422.jpg","j6bzhlT4WstNqJiNuifc8w==":"giphy%20(5).gif","If9uO4Nrq1pu7wz1s7YoTw==":"dsc-73-2000x1330.jpg","6lLO7diFovZLppUmh+2Fww==":"giphy%20(12).gif","Jp2q8qVAFX+lN0Ub5m2o/A==":"dsc-74-2000x1330.jpg","km+YzX9mSNm7GgmhTFNfEA==":"dsc-84-2000x1330.jpg","q2NYeUlkgHbprLF5dfwpEg==":"dsc-75-2000x1330.jpg","hzSvQZ6LjQtk18OAS6AVGw==":"dsc-94-2000x1330.jpg","OEsijoVGv12DsTaR6NkHWg==":"dsc-95-2000x1330.jpg","19BJHlQvhq0GhMFSkMWHpw==":"dsc-84-2000x1330-800x600.jpg","dwqx8Rnca8KyoO7SaKcclQ==":"dsc-75-2000x1330-800x600.jpg","Kc3n+m8se/A0Jhd9uy1VjQ==":"dsc-74-2000x1330-800x600.jpg","nPDw9h+YnUC4y0DFYT3w7w==":"dsc-95-2000x1330-800x600.jpg","/etjNnFF5HxgXYCGHpneSw==":"giphy%20(11).gif","fETwcZOgcYT+2ESQumQj5Q==":"ezgif.com-gif-maker%20(1).gif","nd9EdJXqmkOmBAfe0aj7DQ==":"giphy%20(9).gif","qSRGxYSSy4477i8DQMi/wA==":"giphy%20(9).gif","DhuIZnAN8TfoG+03v03XGg==":"giphy%20(10).gif","dDREHBnKtJYlDaNisKbxZw==":"dsc-46-2000x1330.jpg","3pukIxxgQdNgZGZ5Dk/TMw==":"giphy%20(14).gif","rryuG+ALqVWbEcCQs6BLEw==":"44906594-fila-di-sigarette-con-filtro-uno-%C3%A8-diverso-posa-a-testa-in-gi%C3%B9-texture-di-sfondo-isolato-su-bianco-1300x866.jpg","Vr6qspIeUr4iZA6773/TXQ==":"giphy%20(4).gif","Q5RIvuGJ8nw39JWqQhOJlA==":"mbr-1920x1276.jpg","8SFLFXCq+MZasRUOu/zIQg==":"mbr-1-1920x1271.jpg","VvD9gZ63R3F0/B+HV0NCdQ==":"42512539_2315082018521291_1104971613540974592_n-280x496.jpg","Yt8lkPrSnDPoF/0Zs1HOGA==":"imageedit-11.gif","tVazxiQ4vEiXkHLxo2gyeA==":"ezgif.com-gif-maker.gif"}